bekzod_kutubxona/__init__.py
bekzod_kutubxona/mehmonhona_fayl.py
bekzod_kutubxonasi-0.2.dist-info/METADATA
bekzod_kutubxonasi-0.2.dist-info/WHEEL
bekzod_kutubxonasi-0.2.dist-info/top_level.txt
bekzod_kutubxonasi-0.2.dist-info/RECORD
