Metadata-Version: 2.4
Name: bekzod_kutubxonasi
Version: 0.2
Summary: Loyihalar va metodlarni o'z ichiga olgan oddiy kutubxona
Author: Asqarov Bekzod
Classifier: Programming Language :: Python :: 3
Classifier: License :: OSI Approved :: MIT License
Classifier: Operating System :: OS Independent
Dynamic: author
Dynamic: classifier
Dynamic: summary
